pyvest/__init__.py
pyvest/data_reader/__init__.py
pyvest/data_reader/factors_data_reader.py
pyvest/data_reader/fama_french_data_reader.py
pyvest/data_reader/history_data_reader.py
pyvest/data_reader/returns_data_reader.py
pyvest/data_reader/y_f_data_reader.py
pyvest/factor_model/__init__.py
pyvest/factor_model/capm.py
pyvest/factor_model/factor_model.py
pyvest/factor_model/factor_model_visualizer.py
pyvest/factor_model/ff3f.py
pyvest/factor_model/regression.py
pyvest/general/__init__.py
pyvest/general/general.py
pyvest/general/portfolio.py
pyvest/investment/__init__.py
pyvest/investment/asset.py
pyvest/investment/investment.py
pyvest/investment/investment_dated_info.py
pyvest/investment/investment_state.py
pyvest/investment/investment_visualizer.py
pyvest/investment/profit.py
pyvest/investment/transaction.py
pyvest/investment_universe/__init__.py
pyvest/investment_universe/investment_universe.py
pyvest/investment_universe/investment_universe_visualizer.py
pyvest/investment_universe/investor.py
pyvest/investment_universe/portfolios_generator.py
pyvest/simulation/__init__.py
pyvest/simulation/simulation.py
pyvest-0.0.7.dist-info/licenses/LICENSE.txt
pyvest-0.0.7.dist-info/METADATA
pyvest-0.0.7.dist-info/WHEEL
pyvest-0.0.7.dist-info/top_level.txt
pyvest-0.0.7.dist-info/RECORD
