Metadata-Version: 2.4
Name: pyvest
Version: 0.0.7
Summary: PyVest is a Python library that provides tools for investment analysis.
Author-email: Patrick Munroe <patrick.munroe@gmail.com>, Sébastien Plante <mrplante@hotmail.com>
Maintainer-email: Patrick Munroe <patrick.munroe@gmail.com>
License: MIT
Project-URL: Homepage, https://github.com/pamun/pyvest
Keywords: finance,investment,portfolio theory
Classifier: Programming Language :: Python :: 3
Classifier: License :: OSI Approved :: MIT License
Classifier: Operating System :: OS Independent
Requires-Python: >=3.7
License-File: LICENSE.txt
Requires-Dist: matplotlib
Requires-Dist: scipy
Requires-Dist: numpy
Requires-Dist: pandas
Requires-Dist: yfinance
Requires-Dist: statsmodels
Requires-Dist: pandas-datareader
Dynamic: license-file
